{
  "condition": "C1_full",
  "seed": 2,
  "model": "bert-large",
  "epochs": [
    {
      "epoch": 1,
      "loss": 1.439621636370347,
      "arc_easy": 0.4614035087719298,
      "arc_challenge": 0.27759197324414714
    },
    {
      "epoch": 2,
      "loss": 1.2312267760247415,
      "arc_easy": 0.543859649122807,
      "arc_challenge": 0.34782608695652173
    },
    {
      "epoch": 3,
      "loss": 0.8781728440480775,
      "arc_easy": 0.5614035087719298,
      "arc_challenge": 0.3745819397993311
    },
    {
      "epoch": 4,
      "loss": 0.5473795569108985,
      "arc_easy": 0.5877192982456141,
      "arc_challenge": 0.4013377926421405
    },
    {
      "epoch": 5,
      "loss": 0.3479379559889153,
      "arc_easy": 0.5807017543859649,
      "arc_challenge": 0.3745819397993311
    },
    {
      "epoch": 6,
      "loss": 0.21912367884908313,
      "arc_easy": 0.5614035087719298,
      "arc_challenge": 0.411371237458194
    },
    {
      "epoch": 7,
      "loss": 0.1489318527249008,
      "arc_easy": 0.5596491228070175,
      "arc_challenge": 0.39464882943143814
    },
    {
      "epoch": 8,
      "loss": 0.0894619840306508,
      "arc_easy": 0.5561403508771929,
      "arc_challenge": 0.39464882943143814
    },
    {
      "epoch": 9,
      "loss": 0.07946450542394771,
      "arc_easy": 0.5578947368421052,
      "arc_challenge": 0.391304347826087
    },
    {
      "epoch": 10,
      "loss": 0.07067980071255191,
      "arc_easy": 0.5596491228070175,
      "arc_challenge": 0.3979933110367893
    }
  ],
  "final": {
    "arc_easy_val": 0.5596491228070175,
    "arc_challenge_val": 0.3979933110367893,
    "arc_challenge_test": 0.3796928327645051,
    "n_train": 3370
  },
  "time_sec": 885.1895952224731
}